{"children":[{"condition":"=CN","children":[{"condition":"=JP","children":[{"condition":"->1~300","children":[{"result":["5bffaec57ad3af4fc98e0cfc"],"condition":"=*","attr":"arrWeather"},{"result":["5bffaec57ad3af4fc98e0cfc"],"condition":"=雨","attr":"arrWeather"},{"result":["5bffaec57ad3af4fc98e0cfc"],"condition":"=雪","attr":"arrWeather"}],"attr":"duringMinutes"},{"condition":"->300~600","children":[{"result":["5bffaec57ad3af4fc98e0cfc"],"condition":"=*","attr":"arrWeather"},{"result":["5bffaec57ad3af4fc98e0cfc"],"condition":"=雨","attr":"arrWeather"},{"result":["5bffaec57ad3af4fc98e0cfc"],"condition":"=雪","attr":"arrWeather"}],"attr":"duringMinutes"},{"condition":"->600~999","children":[{"result":["5bffaec57ad3af4fc98e0cfc"],"condition":"=*","attr":"arrWeather"},{"result":["5bffaec57ad3af4fc98e0cfc"],"condition":"=雨","attr":"arrWeather"},{"result":["5bffaec57ad3af4fc98e0cfc"],"condition":"=雪","attr":"arrWeather"}],"attr":"duringMinutes"},{"condition":"->0~1","children":[{"result":["5bffaec57ad3af4fc98e0cf7"],"condition":"=雨","attr":"arrWeather"},{"result":["5bffaec57ad3af4fc98e0cfa"],"condition":"=雪","attr":"arrWeather"},{"result":["5bffaec57ad3af4fc98e0cf7,5bffaec57ad3af4fc98e0cfa"],"condition":"=Negative","attr":"arrWeather"}],"attr":"duringMinutes"}],"attr":"arrCountryCode"},{"condition":"=KR","children":[{"condition":"->1~300","children":[{"result":["5bffaec57ad3af4fc98e0cfc"],"condition":"=*","attr":"arrWeather"},{"result":["5bffaec57ad3af4fc98e0cfc"],"condition":"=雨","attr":"arrWeather"},{"result":["5bffaec57ad3af4fc98e0cfc"],"condition":"=雪","attr":"arrWeather"}],"attr":"duringMinutes"},{"condition":"->300~600","children":[{"result":["5bffaec57ad3af4fc98e0cfc"],"condition":"=*","attr":"arrWeather"},{"result":["5bffaec57ad3af4fc98e0cfc"],"condition":"=雨","attr":"arrWeather"},{"result":["5bffaec57ad3af4fc98e0cfc"],"condition":"=雪","attr":"arrWeather"}],"attr":"duringMinutes"},{"condition":"->600~999","children":[{"result":["5bffaec57ad3af4fc98e0cfc"],"condition":"=*","attr":"arrWeather"},{"result":["5bffaec57ad3af4fc98e0cfc"],"condition":"=雨","attr":"arrWeather"},{"result":["5bffaec57ad3af4fc98e0cfc"],"condition":"=雪","attr":"arrWeather"}],"attr":"duringMinutes"},{"condition":"->0~1","children":[{"result":["5bffaec57ad3af4fc98e0cf7"],"condition":"=雨","attr":"arrWeather"},{"result":["5bffaec57ad3af4fc98e0cfa"],"condition":"=雪","attr":"arrWeather"},{"result":["5bffaec57ad3af4fc98e0cf7,5bffaec57ad3af4fc98e0cfa"],"condition":"=Negative","attr":"arrWeather"}],"attr":"duringMinutes"}],"attr":"arrCountryCode"},{"condition":"=US","children":[{"condition":"->1~300","children":[{"result":["5bffaec57ad3af4fc98e0cfc"],"condition":"=*","attr":"arrWeather"},{"result":["5bffaec57ad3af4fc98e0cfc"],"condition":"=雨","attr":"arrWeather"},{"result":["5bffaec57ad3af4fc98e0cfc"],"condition":"=雪","attr":"arrWeather"}],"attr":"duringMinutes"},{"condition":"->300~600","children":[{"result":["5bffaec57ad3af4fc98e0cfc"],"condition":"=*","attr":"arrWeather"},{"result":["5bffaec57ad3af4fc98e0cfc"],"condition":"=雨","attr":"arrWeather"},{"result":["5bffaec57ad3af4fc98e0cfc"],"condition":"=雪","attr":"arrWeather"}],"attr":"duringMinutes"},{"condition":"->600~999","children":[{"result":["5bffaec57ad3af4fc98e0cfc"],"condition":"=*","attr":"arrWeather"},{"result":["5bffaec57ad3af4fc98e0cfc"],"condition":"=雨","attr":"arrWeather"},{"result":["5bffaec57ad3af4fc98e0cfc"],"condition":"=雪","attr":"arrWeather"}],"attr":"duringMinutes"},{"condition":"->0~1","children":[{"result":["5bffaec57ad3af4fc98e0cf7"],"condition":"=雨","attr":"arrWeather"},{"result":["5bffaec57ad3af4fc98e0cfa"],"condition":"=雪","attr":"arrWeather"},{"result":["5bffaec57ad3af4fc98e0cf7,5bffaec57ad3af4fc98e0cfa"],"condition":"=Negative","attr":"arrWeather"}],"attr":"duringMinutes"}],"attr":"arrCountryCode"},{"condition":"=*","children":[{"condition":"->0~1","children":[{"result":["5bffaec57ad3af4fc98e0cf7"],"condition":"=雨","attr":"arrWeather"},{"result":["5bffaec57ad3af4fc98e0cfa"],"condition":"=雪","attr":"arrWeather"},{"result":["5bffaec57ad3af4fc98e0cf7,5bffaec57ad3af4fc98e0cfa"],"condition":"=Negative","attr":"arrWeather"}],"attr":"duringMinutes"},{"condition":"->1~300","children":[{"result":["5bffaec57ad3af4fc98e0cfc"],"condition":"=雨","attr":"arrWeather"},{"result":["5bffaec57ad3af4fc98e0cfc"],"condition":"=雪","attr":"arrWeather"},{"result":["5bffaec57ad3af4fc98e0cfc"],"condition":"=*","attr":"arrWeather"}],"attr":"duringMinutes"},{"condition":"->300~600","children":[{"result":["5bffaec57ad3af4fc98e0cfc"],"condition":"=雨","attr":"arrWeather"},{"result":["5bffaec57ad3af4fc98e0cfc"],"condition":"=*","attr":"arrWeather"},{"result":["5bffaec57ad3af4fc98e0cfc"],"condition":"=雪","attr":"arrWeather"}],"attr":"duringMinutes"},{"result":["5bffaec57ad3af4fc98e0cfc"],"condition":"->600~999","attr":"duringMinutes"}],"attr":"arrCountryCode"},{"condition":"=CN","children":[{"condition":"=雨","children":[{"result":["5bffaec57ad3af4fc98e0cf7"],"condition":"->0~1","attr":"duringMinutes"},{"result":["5bffaec57ad3af4fc98e0cfc"],"condition":"->1~300","attr":"duringMinutes"},{"result":["5bffaec57ad3af4fc98e0cfc"],"condition":"->300~600","attr":"duringMinutes"},{"result":["5bffaec57ad3af4fc98e0cfc"],"condition":"->600~999","attr":"duringMinutes"}],"attr":"arrWeather"},{"condition":"=雪","children":[{"condition":"->0~1","children":[{"result":["5bffaec57ad3af4fc98e0cf8"],"condition":"->6~144","attr":"beforeDepartHour"},{"result":["5bffaec57ad3af4fc98e0cfa"],"condition":"->144~99999","attr":"beforeDepartHour"},{"result":["5bffaec57ad3af4fc98e0cf8,5bffaec57ad3af4fc98e0cfa"],"condition":"=Negative","attr":"beforeDepartHour"}],"attr":"duringMinutes"},{"result":["5bffaec57ad3af4fc98e0cfc"],"condition":"->1~300","attr":"duringMinutes"},{"result":["5bffaec57ad3af4fc98e0cfc"],"condition":"->300~600","attr":"duringMinutes"},{"result":["5bffaec57ad3af4fc98e0cfc"],"condition":"->600~999","attr":"duringMinutes"}],"attr":"arrWeather"},{"condition":"=*","children":[{"result":["5bffaec57ad3af4fc98e0cfc"],"condition":"->1~300","attr":"duringMinutes"},{"result":["5bffaec57ad3af4fc98e0cfc"],"condition":"->300~600","attr":"duringMinutes"},{"result":["5bffaec57ad3af4fc98e0cfc"],"condition":"->600~999","attr":"duringMinutes"}],"attr":"arrWeather"}],"attr":"arrCountryCode"}],"attr":"depCountryCode"},{"condition":"=*","children":[{"condition":"=雨","children":[{"result":["5bffaec57ad3af4fc98e0cf7"],"condition":"->0~1","attr":"duringMinutes"},{"result":["5bffaec57ad3af4fc98e0cfc"],"condition":"->1~300,600~999,300~600","attr":"duringMinutes"},{"result":["5bffaec57ad3af4fc98e0cf7,5bffaec57ad3af4fc98e0cfc"],"condition":"=Negative","attr":"duringMinutes"}],"attr":"arrWeather"},{"condition":"=雪","children":[{"result":["5bffaec57ad3af4fc98e0cfa"],"condition":"->0~1","attr":"duringMinutes"},{"result":["5bffaec57ad3af4fc98e0cfc"],"condition":"->1~300","attr":"duringMinutes"},{"result":["5bffaec57ad3af4fc98e0cfc"],"condition":"->300~600","attr":"duringMinutes"},{"result":["5bffaec57ad3af4fc98e0cfc"],"condition":"->600~999","attr":"duringMinutes"}],"attr":"arrWeather"},{"result":["5bffaec57ad3af4fc98e0cfc"],"condition":"=*","attr":"arrWeather"}],"attr":"depCountryCode"}]}